robustloss/__init__.py
robustloss/apply_noise.py
robustloss/apply_outliers.py
robustloss/datamod.py
robustloss/loss_functions.py
robustloss/models.py
robustloss/noise_types.py
robustloss/outliers.py
robustloss/preprocess.py
robustloss/registry.py
robustloss/schemas.py
robustloss/train_many.py
robustloss_lab-2.1.5.dist-info/licenses/LICENSE
robustloss_lab-2.1.5.dist-info/METADATA
robustloss_lab-2.1.5.dist-info/WHEEL
robustloss_lab-2.1.5.dist-info/top_level.txt
robustloss_lab-2.1.5.dist-info/RECORD
